pyxpdf_data/__init__.py
pyxpdf_data/encodings.py
pyxpdf_data/fonts.py
pyxpdf_data/utils.py
pyxpdf_data/fonts/C059-BdIta.ttf
pyxpdf_data/fonts/C059-Bold.ttf
pyxpdf_data/fonts/C059-Italic.ttf
pyxpdf_data/fonts/C059-Roman.ttf
pyxpdf_data/fonts/COPYING.affero
pyxpdf_data/fonts/D050000L.ttf
pyxpdf_data/fonts/NimbusMonoPS-Bold.ttf
pyxpdf_data/fonts/NimbusMonoPS-BoldItalic.ttf
pyxpdf_data/fonts/NimbusMonoPS-Italic.ttf
pyxpdf_data/fonts/NimbusMonoPS-Regular.ttf
pyxpdf_data/fonts/NimbusRoman-Bold.ttf
pyxpdf_data/fonts/NimbusRoman-BoldItalic.ttf
pyxpdf_data/fonts/NimbusRoman-Italic.ttf
pyxpdf_data/fonts/NimbusRoman-Regular.ttf
pyxpdf_data/fonts/NimbusSans-Bold.ttf
pyxpdf_data/fonts/NimbusSans-BoldItalic.ttf
pyxpdf_data/fonts/NimbusSans-Italic.ttf
pyxpdf_data/fonts/NimbusSans-Regular.ttf
pyxpdf_data/fonts/NimbusSansNarrow-BdOblique.ttf
pyxpdf_data/fonts/NimbusSansNarrow-Bold.ttf
pyxpdf_data/fonts/NimbusSansNarrow-Oblique.ttf
pyxpdf_data/fonts/NimbusSansNarrow-Regular.ttf
pyxpdf_data/fonts/P052-Bold.ttf
pyxpdf_data/fonts/P052-BoldItalic.ttf
pyxpdf_data/fonts/P052-Italic.ttf
pyxpdf_data/fonts/P052-Roman.ttf
pyxpdf_data/fonts/StandardSymbolsPS.ttf
pyxpdf_data/fonts/URWBookman-Demi.ttf
pyxpdf_data/fonts/URWBookman-DemiItalic.ttf
pyxpdf_data/fonts/URWBookman-Light.ttf
pyxpdf_data/fonts/URWBookman-LightItalic.ttf
pyxpdf_data/fonts/URWGothic-Book.ttf
pyxpdf_data/fonts/URWGothic-BookOblique.ttf
pyxpdf_data/fonts/URWGothic-Demi.ttf
pyxpdf_data/fonts/URWGothic-DemiOblique.ttf
pyxpdf_data/fonts/Z003-MediumItalic.ttf
pyxpdf_data/poppler_data/.git
pyxpdf_data/poppler_data/.gitignore
pyxpdf_data/poppler_data/CMakeLists.txt
pyxpdf_data/poppler_data/COPYING
pyxpdf_data/poppler_data/COPYING.adobe
pyxpdf_data/poppler_data/COPYING.gpl2
pyxpdf_data/poppler_data/Makefile
pyxpdf_data/poppler_data/README
pyxpdf_data/poppler_data/poppler-data.pc.in
pyxpdf_data/poppler_data/cMap/Adobe-CNS1/Adobe-CNS1-0
pyxpdf_data/poppler_data/cMap/Adobe-CNS1/Adobe-CNS1-1
pyxpdf_data-1.1.0.dist-info/LICENSE
pyxpdf_data-1.1.0.dist-info/METADATA
pyxpdf_data-1.1.0.dist-info/WHEEL
pyxpdf_data-1.1.0.dist-info/top_level.txt
pyxpdf_data-1.1.0.dist-info/RECORD
