Metadata-Version: 2.1
Name: pyxpdf-data
Version: 1.1.0
Summary: This package contains additional encoding files for pyxpdf. (credit poppler_data)
Home-page: https://github.com/ashutoshvarma/pyxpdf_data
Author: Ashutosh Varma
Author-email: ashutoshvarma11@live.com
License: MIT
Platform: UNKNOWN
Classifier: Programming Language :: Python
Classifier: Programming Language :: Python :: 3.4
Classifier: Programming Language :: Python :: 3.5
Classifier: Programming Language :: Python :: 3.6
Classifier: Programming Language :: Python :: 3 :: Only
Classifier: License :: OSI Approved :: MIT License
Classifier: Development Status :: 5 - Production/Stable
Classifier: Topic :: Text Processing
